cosin_helpers/__init__.py
cosin_helpers/__main__.py
cosin_helpers/core/__init__.py
cosin_helpers/core/version.py
cosin_helpers/main.py
cosin_helpers/plugins/__init__.py
cosin_helpers/plugins/briltools/__init__.py
cosin_helpers/plugins/briltools/briltools.py
cosin_helpers/plugins/briltools/typer_interface.py
cosin_helpers/plugins/dataset_paths/__init__.py
cosin_helpers/plugins/dataset_paths/dataset_paths.py
cosin_helpers/plugins/dataset_paths/typer_interface.py
cosin_helpers/plugins/sumw/__init__.py
cosin_helpers/plugins/sumw/sumw.py
cosin_helpers/plugins/sumw/typer_interface.py
cosin_helpers-0.1.3.dist-info/METADATA
cosin_helpers-0.1.3.dist-info/WHEEL
cosin_helpers-0.1.3.dist-info/entry_points.txt
cosin_helpers-0.1.3.dist-info/RECORD
