Metadata-Version: 2.3
Name: cosin_helpers
Version: 0.1.3
Summary: Helpers for CMS tools that can be ran on lxplus
Author: Nico Toikka
Author-email: nico.toikka@helsinki.fi
Requires-Python: >=3.9
Classifier: Programming Language :: Python :: 3
Classifier: Programming Language :: Python :: 3.9
Classifier: Programming Language :: Python :: 3.10
Classifier: Programming Language :: Python :: 3.11
Classifier: Programming Language :: Python :: 3.12
Classifier: Programming Language :: Python :: 3.13
Requires-Dist: pandas (>=2.3.1,<3.0.0)
Requires-Dist: typer (>=0.16.0,<0.17.0)
Requires-Dist: uproot (>=5.6.4,<6.0.0)
